based_utils/__init__.py
based_utils/algo/__init__.py
based_utils/algo/cycles.py
based_utils/algo/paths.py
based_utils/class_utils.py
based_utils/cli/__init__.py
based_utils/cli/args.py
based_utils/cli/clox.py
based_utils/cli/exec.py
based_utils/cli/io.py
based_utils/cli/logs.py
based_utils/concurrency.py
based_utils/data.py
based_utils/interpol.py
based_utils/iterators.py
based_utils/keyboard.py
based_utils/math.py
based_utils/misc/__init__.py
based_utils/misc/music.py
based_utils/py.typed
based_utils-1.0.21.dist-info/WHEEL
based_utils-1.0.21.dist-info/entry_points.txt
based_utils-1.0.21.dist-info/METADATA
based_utils-1.0.21.dist-info/RECORD
