Metadata-Version: 2.4
Name: based-utils
Version: 1.0.21
Summary: Add your description here
Keywords: base utilities
Author: Huib Piguillet
Author-email: Huib Piguillet <huib@proton.me>
License-Expression: MIT
Classifier: Intended Audience :: Developers
Classifier: Topic :: Utilities
Classifier: Programming Language :: Python :: 3
Classifier: Programming Language :: Python :: 3.12
Classifier: Programming Language :: Python :: 3.13
Classifier: Programming Language :: Python :: 3.14
Classifier: Programming Language :: Python :: 3 :: Only
Requires-Dist: more-itertools ; extra == 'iter'
Requires-Dist: pynput ; extra == 'keyboard'
Requires-Python: >=3.14
Project-URL: Github, https://github.com/githuib/based-utils/
Project-URL: PyPI, https://pypi.org/project/based-utils/
Provides-Extra: iter
Provides-Extra: keyboard
